lgt_data/__init__.py
lgt_data/analytics.py
lgt_data/engine.py
lgt_data/enums.py
lgt_data/helpers.py
lgt_data/model.py
lgt_data/mongo_repository.py
leadguru_data-0.390.0.dist-info/METADATA
leadguru_data-0.390.0.dist-info/WHEEL
leadguru_data-0.390.0.dist-info/top_level.txt
leadguru_data-0.390.0.dist-info/RECORD
