Metadata-Version: 2.1
Name: leadguru-data
Version: 0.390.0
Summary: LGT data builds
Author-email: developer@leadguru.co
Requires-Dist: wheel
Requires-Dist: pymongo
Requires-Dist: python-dateutil
Requires-Dist: nameparser
Requires-Dist: mongoengine
